crystal/__init__.py
crystal/__main__.py
crystal/app_preferences.py
crystal/browser/__init__.py
crystal/browser/about.py
crystal/browser/entitytree.py
crystal/browser/icons.py
crystal/browser/new_group.py
crystal/browser/new_root_url.py
crystal/browser/preferences.py
crystal/browser/tasktree.py
crystal/doc/__init__.py
crystal/doc/css.py
crystal/doc/generic.py
crystal/doc/html/__init__.py
crystal/doc/html/basic.py
crystal/doc/html/soup.py
crystal/doc/json.py
crystal/doc/xml.py
crystal/download.py
crystal/install.py
crystal/main.py
crystal/model.py
crystal/plugins/__init__.py
crystal/plugins/minimalist_baker.py
crystal/plugins/phpbb.py
crystal/plugins/substack.py
crystal/plugins/util/__init__.py
crystal/plugins/util/params.py
crystal/plugins/wordpress.py
crystal/predict_group.py
crystal/progress.py
crystal/py.typed
crystal/resources/__init__.py
crystal/resources/appicon--fallback.svg
crystal/resources/appicon.ico
crystal/resources/appicon.png
crystal/resources/application-vnd.crystal.opener.png
crystal/resources/application-vnd.crystal.opener.svg
crystal/resources/application-vnd.crystal.opener.svg-README.txt
crystal/resources/application-vnd.crystal.opener.xml
crystal/resources/application-vnd.crystal.opener_128x128.png
crystal/resources/application-vnd.crystal.opener_128x128.svg
crystal/resources/application-vnd.crystal.opener_16x16.png
crystal/resources/application-vnd.crystal.opener_16x16.svg
crystal/resources/application-vnd.crystal.opener_22x22.png
crystal/resources/application-vnd.crystal.opener_22x22.svg
crystal/resources/application-vnd.crystal.opener_32x32.png
crystal/resources/application-vnd.crystal.opener_32x32.svg
crystal/resources/application-vnd.crystal.opener_44x44.png
crystal/resources/application-vnd.crystal.opener_44x44.svg
crystal/resources/application-vnd.crystal.opener_64x64.png
crystal/resources/application-vnd.crystal.opener_64x64.svg
crystal/resources/badge_new.png
crystal/resources/badge_prohibition.png
crystal/resources/badge_stale.png
crystal_web-2.1.0.dist-info/LICENSE.txt
crystal_web-2.1.0.dist-info/METADATA
crystal_web-2.1.0.dist-info/WHEEL
crystal_web-2.1.0.dist-info/entry_points.txt
crystal_web-2.1.0.dist-info/RECORD
