Metadata-Version: 2.3
Name: crystal-web
Version: 2.1.0
Summary: Downloads websites for long-term archival.
License: PolyForm-Noncommercial-1.0.0
Author: David Foster
Author-email: david@dafoster.net
Requires-Python: >=3.11,<3.14
Classifier: Development Status :: 5 - Production/Stable
Classifier: Environment :: MacOS X
Classifier: Environment :: Win32 (MS Windows)
Classifier: Environment :: X11 Applications
Classifier: Environment :: X11 Applications :: GTK
Classifier: Environment :: X11 Applications :: Gnome
Classifier: Environment :: X11 Applications :: KDE
Classifier: Intended Audience :: End Users/Desktop
Classifier: Intended Audience :: Information Technology
Classifier: Intended Audience :: System Administrators
Classifier: License :: Free for non-commercial use
Classifier: Natural Language :: English
Classifier: Operating System :: MacOS :: MacOS X
Classifier: Operating System :: Microsoft :: Windows
Classifier: Operating System :: Microsoft :: Windows :: Windows 11
Classifier: Operating System :: POSIX :: Linux
Classifier: Topic :: Internet :: WWW/HTTP
Classifier: Topic :: Internet :: WWW/HTTP :: Browsers
Classifier: Topic :: Software Development :: Version Control
Classifier: Topic :: System :: Archiving :: Backup
Classifier: Topic :: System :: Archiving :: Mirroring
Requires-Dist: PySocks (>=1.7.1,<2.0.0)
Requires-Dist: appdirs (>=1.4.4,<2.0.0)
Requires-Dist: beautifulsoup4 (>=4.9.3,<5.0.0)
Requires-Dist: colorama (>=0.4.4,<0.5.0)
Requires-Dist: guppy3 (>=3.1.5,<4.0.0)
Requires-Dist: jaraco-text (>=4.0.0)
Requires-Dist: lxml (>=5.2.2,<6.0.0)
Requires-Dist: psutil (>=5.9.5,<6.0.0) ; sys_platform == "linux"
Requires-Dist: py2app (>=0.28,<0.29) ; sys_platform == "darwin"
Requires-Dist: py2exe (>=0.14.0.0,<0.15.0.0) ; sys_platform == "win32" and python_version >= "3.11"
Requires-Dist: pywin32 ; sys_platform == "win32"
Requires-Dist: send2trash (>=1.8.3,<2.0.0)
Requires-Dist: sortedcontainers (>=2.4.0,<3.0.0)
Requires-Dist: tinycss2 (>=1.1.0,<2.0.0)
Requires-Dist: tqdm (>=4.65.0,<5.0.0)
Requires-Dist: truststore
Requires-Dist: trycast (>=1.2.1,<2.0.0)
Requires-Dist: types-tqdm (>=4.66.0.20240106,<5.0.0.0)
Requires-Dist: typing-extensions (>=4.8.0,<5.0.0)
Requires-Dist: tzlocal (>=4.2,<5.0)
Requires-Dist: wakepy (>=0.9.0,<0.10.0)
Requires-Dist: wmi ; sys_platform == "win32"
Requires-Dist: wxPython (==4.2.3)
Requires-Dist: xattr (>=1.1.4,<2.0.0) ; sys_platform == "darwin"
Project-URL: Bug tracker, https://github.com/davidfstr/Crystal-Web-Archiver/issues
Project-URL: Documentation, https://github.com/davidfstr/Crystal-Web-Archiver/wiki
Project-URL: Homepage, https://dafoster.net/projects/crystal-web-archiver/
Project-URL: Repository, https://github.com/davidfstr/Crystal-Web-Archiver
Project-URL: Release notes, https://github.com/davidfstr/Crystal-Web-Archiver/blob/main/RELEASE_NOTES.md
Project-URL: Tutorial, https://github.com/davidfstr/Crystal-Web-Archiver/tree/main#tutorial-
